Metadata-Version: 2.1
Name: xmdaikz
Version: 1.0
Summary: pg2 TTS
Home-page: UNKNOWN
Author: iduarte
Author-email: irving.duarte@outlook.com
License: UNKNOWN
Platform: UNKNOWN
